welcomepackage-0.0.2.dist-info/METADATA
welcomepackage-0.0.2.dist-info/WHEEL
welcomepackage-0.0.2.dist-info/entry_points.txt
welcomepackage/__init__.py
welcomepackage/tui.py
welcomepackage-0.0.2.dist-info/RECORD
