Metadata-Version: 2.1
Name: welcomepackage
Version: 0.0.2
Summary: Minimal TUI ready for cross-platform packaging as a pure-Python zipapp.
Author-Email: David Seaward <david@librem.one>
License: CC0-1.0
Requires-Python: >=3.10
Requires-Dist: textual>=0.40.0
